bandyt/__init__.py
bandyt/bandyt.py
bandyt/bnomics.py
bandyt/bnutils.py
bandyt/dutils.py
bandyt/ofext.cpp
bandyt/ofext.so
bandyt/oflib.py
bandyt/ofunc.py
bandyt/synthetic.py
bandyt-0.23.dist-info/LICENSE.txt
bandyt-0.23.dist-info/METADATA
bandyt-0.23.dist-info/WHEEL
bandyt-0.23.dist-info/top_level.txt
bandyt-0.23.dist-info/RECORD
