Metadata-Version: 2.1
Name: bandyt
Version: 0.23
Summary: A brief description of your module
Home-page: https://github.com/bandyt-group/bandyt
Author: Elizaveta Mukhaleva, Babgen Manookian, Konstancja Urbaniak, Grigoriy Gogoshin, Nagarajan Vaidehi, Andrei Rodin, Sergio Branciamore
Author-email: bandyt-group@gmail.com
License: MIT
Classifier: Programming Language :: Python :: 3
Classifier: License :: OSI Approved :: MIT License
Classifier: Operating System :: OS Independent
Requires-Python: >=3.6
License-File: LICENSE.txt
Requires-Dist: numpy
Requires-Dist: pandas
Requires-Dist: seaborn
Requires-Dist: matplotlib
Requires-Dist: pydot
Requires-Dist: igraph
